odoo/addons/ssi_l10n_id_taxform_bukti_potong_pph_f113302/README.rst
odoo/addons/ssi_l10n_id_taxform_bukti_potong_pph_f113302/__init__.py
odoo/addons/ssi_l10n_id_taxform_bukti_potong_pph_f113302/__manifest__.py
odoo/addons/ssi_l10n_id_taxform_bukti_potong_pph_f113302/data/account_journal_data.xml
odoo/addons/ssi_l10n_id_taxform_bukti_potong_pph_f113302/data/approval_template_data.xml
odoo/addons/ssi_l10n_id_taxform_bukti_potong_pph_f113302/data/ir_sequence_data.xml
odoo/addons/ssi_l10n_id_taxform_bukti_potong_pph_f113302/data/l10n_id_bukti_potong_type.xml
odoo/addons/ssi_l10n_id_taxform_bukti_potong_pph_f113302/data/policy_template_data.xml
odoo/addons/ssi_l10n_id_taxform_bukti_potong_pph_f113302/data/sequence_template_data.xml
odoo/addons/ssi_l10n_id_taxform_bukti_potong_pph_f113302/demo/account_account_demo.xml
odoo/addons/ssi_l10n_id_taxform_bukti_potong_pph_f113302/demo/account_journal_demo.xml
odoo/addons/ssi_l10n_id_taxform_bukti_potong_pph_f113302/demo/account_tax_demo.xml
odoo/addons/ssi_l10n_id_taxform_bukti_potong_pph_f113302/demo/l10n_id_bukti_potong_type_demo.xml
odoo/addons/ssi_l10n_id_taxform_bukti_potong_pph_f113302/models/__init__.py
odoo/addons/ssi_l10n_id_taxform_bukti_potong_pph_f113302/models/bukti_potong_pph_f113302_out.py
odoo/addons/ssi_l10n_id_taxform_bukti_potong_pph_f113302/models/bukti_potong_pph_f113302_out_line.py
odoo/addons/ssi_l10n_id_taxform_bukti_potong_pph_f113302/security/ir.model.access.csv
odoo/addons/ssi_l10n_id_taxform_bukti_potong_pph_f113302/security/ir_module_category_data.xml
odoo/addons/ssi_l10n_id_taxform_bukti_potong_pph_f113302/security/ir_rule_data.xml
odoo/addons/ssi_l10n_id_taxform_bukti_potong_pph_f113302/security/res_group_data.xml
odoo/addons/ssi_l10n_id_taxform_bukti_potong_pph_f113302/static/description/icon.png
odoo/addons/ssi_l10n_id_taxform_bukti_potong_pph_f113302/views/bukti_potong_pph_f113302_out_views.xml
odoo/addons/ssi_l10n_id_taxform_bukti_potong_pph_f113302/views/bukti_potong_pph_type_views.xml
odoo14_addon_ssi_l10n_id_taxform_bukti_potong_pph_f113302-14.0.1.6.0.dist-info/METADATA
odoo14_addon_ssi_l10n_id_taxform_bukti_potong_pph_f113302-14.0.1.6.0.dist-info/WHEEL
odoo14_addon_ssi_l10n_id_taxform_bukti_potong_pph_f113302-14.0.1.6.0.dist-info/top_level.txt
odoo14_addon_ssi_l10n_id_taxform_bukti_potong_pph_f113302-14.0.1.6.0.dist-info/RECORD
